<annotation>
  <folder>after_argument</folder>
  <filename>4022_arg_0.jpg</filename>
  <path>4022_arg_0.jpg</path>
  <source/>
  <database>Unknown</database>
  <size>
    <width>1280</width>
    <height>720</height>
    <depth>3</depth>
  </size>
  <object>
    <name>speed_limited</name>
    <bndbox>
      <xmin>1072</xmin>
      <ymin>408</ymin>
      <xmax>1179</xmax>
      <ymax>531</ymax>
    </bndbox>
  </object>
  <object>
    <name>speed_unlimited</name>
    <bndbox>
      <xmin>625</xmin>
      <ymin>443</ymin>
      <xmax>676</xmax>
      <ymax>511</ymax>
    </bndbox>
  </object>
  <object>
    <name>green_go</name>
    <bndbox>
      <xmin>860</xmin>
      <ymin>438</ymin>
      <xmax>910</xmax>
      <ymax>527</ymax>
    </bndbox>
  </object>
  <object>
    <name>red_stop</name>
    <bndbox>
      <xmin>182</xmin>
      <ymin>18</ymin>
      <xmax>408</xmax>
      <ymax>298</ymax>
    </bndbox>
  </object>
</annotation>
