<annotation>
  <folder>after_argument</folder>
  <filename>4027_arg_1.jpg</filename>
  <path>4027_arg_1.jpg</path>
  <source/>
  <database>Unknown</database>
  <size>
    <width>1280</width>
    <height>720</height>
    <depth>3</depth>
  </size>
  <object>
    <name>speed_unlimited</name>
    <bndbox>
      <xmin>387</xmin>
      <ymin>343</ymin>
      <xmax>479</xmax>
      <ymax>449</ymax>
    </bndbox>
  </object>
  <object>
    <name>green_go</name>
    <bndbox>
      <xmin>858</xmin>
      <ymin>356</ymin>
      <xmax>933</xmax>
      <ymax>483</ymax>
    </bndbox>
  </object>
</annotation>
