<annotation>
  <folder>after_argument</folder>
  <filename>468_arg_2.jpg</filename>
  <path>468_arg_2.jpg</path>
  <source/>
  <database>Unknown</database>
  <size>
    <width>1280</width>
    <height>720</height>
    <depth>3</depth>
  </size>
  <object>
    <name>speed_limited</name>
    <bndbox>
      <xmin>939</xmin>
      <ymin>358</ymin>
      <xmax>1029</xmax>
      <ymax>457</ymax>
    </bndbox>
  </object>
  <object>
    <name>yellow_back</name>
    <bndbox>
      <xmin>454</xmin>
      <ymin>23</ymin>
      <xmax>623</xmax>
      <ymax>318</ymax>
    </bndbox>
  </object>
</annotation>
