<annotation>
  <folder>after_argument</folder>
  <filename>585_arg_1.jpg</filename>
  <path>585_arg_1.jpg</path>
  <source/>
  <database>Unknown</database>
  <size>
    <width>1280</width>
    <height>720</height>
    <depth>3</depth>
  </size>
  <object>
    <name>pedestrian_crossing</name>
    <bndbox>
      <xmin>394</xmin>
      <ymin>580</ymin>
      <xmax>652</xmax>
      <ymax>645</ymax>
    </bndbox>
  </object>
  <object>
    <name>speed_unlimited</name>
    <bndbox>
      <xmin>785</xmin>
      <ymin>438</ymin>
      <xmax>811</xmax>
      <ymax>479</ymax>
    </bndbox>
  </object>
  <object>
    <name>green_go</name>
    <bndbox>
      <xmin>802</xmin>
      <ymin>145</ymin>
      <xmax>889</xmax>
      <ymax>355</ymax>
    </bndbox>
  </object>
</annotation>
